chat_agent/__init__.py
chat_agent/app.py
chat_agent/base_websocket_app.py
chat_agent/cert.pem
chat_agent/favicon.ico
chat_agent/key.pem
chat_agent/websocket_app.py
chat_agent/base/__init__.py
chat_agent/base/base_websocket.py
chat_agent/base/singleton.py
chat_agent/cache/__init__.py
chat_agent/cache/cache_helper.py
chat_agent/client/__init__.py
chat_agent/client/base_web_socket_client.py
chat_agent/client/web_socket_client.py
chat_agent/config/__init__.py
chat_agent/config/config_helper.py
chat_agent/handler/__init__.py
chat_agent/handler/openai_handler.py
chat_agent/logger/__init__.py
chat_agent/logger/logger_helper.py
chat_agent/static/index.html
chat_agent/static/websocket_index.html
chat_agent/static/icon/openai.png
chat_agent/static/icon/whale.png
chat_agent/test/__init__.py
chat_agent/util/__init__.py
chat_agent/util/context.py
chat_agent/util/file.py
chat_agent/util/random.py
chat_agent/util/time.py
chat_agent/util/timeout.py
chat_agent-0.1.6.7.dist-info/METADATA
chat_agent-0.1.6.7.dist-info/WHEEL
chat_agent-0.1.6.7.dist-info/top_level.txt
chat_agent-0.1.6.7.dist-info/RECORD
